async_pymongo/__init__.py
async_pymongo/async_helper.py
async_pymongo/base.py
async_pymongo/change_stream.py
async_pymongo/client.py
async_pymongo/client_session.py
async_pymongo/collection.py
async_pymongo/command_cursor.py
async_pymongo/cursor.py
async_pymongo/cursor_base.py
async_pymongo/db.py
async_pymongo/errors.py
async_pymongo/typings.py
async_pymongo-0.1.10.dist-info/LICENSE
async_pymongo-0.1.10.dist-info/METADATA
async_pymongo-0.1.10.dist-info/WHEEL
async_pymongo-0.1.10.dist-info/RECORD
